srs_cg635/__init__.py
srs_cg635/common.py
srs_cg635/instrument.py
srs_cg635/version.py
srs_cg635-0.1.3.dist-info/LICENSE
srs_cg635-0.1.3.dist-info/METADATA
srs_cg635-0.1.3.dist-info/WHEEL
srs_cg635-0.1.3.dist-info/top_level.txt
srs_cg635-0.1.3.dist-info/RECORD
