Metadata-Version: 2.1
Name: srs-cg635
Version: 0.1.3
Summary: Communication with SRS CG635
Home-page: https://github.com/l-johnston/srs_cg635
Author: Lee Johnston
Author-email: lee.johnston.100@gmail.com
License: MIT
Platform: UNKNOWN
Classifier: Programming Language :: Python :: 3
Classifier: Topic :: Scientific/Engineering
Classifier: License :: OSI Approved :: MIT License
Classifier: Intended Audience :: Science/Research
Requires-Dist: pyvisa
Requires-Dist: numpy
